mseep_notion_mcp-0.1.3.dist-info/licenses/LICENSE
notion_mcp/__init__.py
notion_mcp/__main__.py
notion_mcp/server.py
mseep_notion_mcp-0.1.3.dist-info/METADATA
mseep_notion_mcp-0.1.3.dist-info/WHEEL
mseep_notion_mcp-0.1.3.dist-info/top_level.txt
mseep_notion_mcp-0.1.3.dist-info/RECORD
