Metadata-Version: 2.4
Name: mseep-notion_mcp
Version: 0.1.3
Summary: Notion MCP integration for todo lists
Author-email: mseep <support@skydeck.ai>
Requires-Python: >=3.10
License-File: LICENSE
Requires-Dist: mcp
Requires-Dist: httpx
Requires-Dist: python-dotenv
Dynamic: license-file
